askxml/__init__.py
askxml/askxml.py
askxml/table.py
askxml/column/__init__.py
askxml/column/data_types.py
askxml/column/keys.py
askxml/driver/__init__.py
askxml/driver/driver.py
askxml/driver/sqlite_driver.py
askxml-1.0.0.dist-info/METADATA
askxml-1.0.0.dist-info/RECORD
askxml-1.0.0.dist-info/WHEEL
askxml-1.0.0.dist-info/top_level.txt
