Metadata-Version: 2.1
Name: askxml
Version: 1.0.0
Summary: Run SQL statements on XML documents
Home-page: https://github.com/kamac/AskXML
Author: Maciej Kozik
License: UNKNOWN
Keywords: xml sql statements query
Platform: UNKNOWN
Classifier: Development Status :: 5 - Production/Stable
Classifier: Intended Audience :: Developers
Classifier: Topic :: Text Processing :: Markup :: XML
Classifier: License :: OSI Approved :: MIT License
Classifier: Programming Language :: Python :: 3.5
Classifier: Programming Language :: Python :: 3.6
Classifier: Programming Language :: Python :: 3.7
